sparrow_tracky/__init__.py
sparrow_tracky/deepsort/__init__.py
sparrow_tracky/deepsort/distance.py
sparrow_tracky/deepsort/distance_test.py
sparrow_tracky/deepsort/multiclass_tracker.py
sparrow_tracky/deepsort/multiclass_tracker_test.py
sparrow_tracky/deepsort/tracker.py
sparrow_tracky/deepsort/tracker_test.py
sparrow_tracky/deepsort/tracklet.py
sparrow_tracky/deepsort/tracklet_test.py
sparrow_tracky/metrics/__init__.py
sparrow_tracky/metrics/moda.py
sparrow_tracky/metrics/moda_test.py
sparrow_tracky/metrics/mota.py
sparrow_tracky/metrics/mota_test.py
sparrow_tracky-1.0.0.dist-info/licenses/LICENSE
sparrow_tracky-1.0.0.dist-info/METADATA
sparrow_tracky-1.0.0.dist-info/WHEEL
sparrow_tracky-1.0.0.dist-info/top_level.txt
sparrow_tracky-1.0.0.dist-info/RECORD
