Metadata-Version: 2.4
Name: sparrow-tracky
Version: 1.0.0
Author: Sparrow Computing
Author-email: ben@sparrow.dev
License-File: LICENSE
Requires-Dist: scipy
Requires-Dist: sparrow-datums>=0.9.3
Provides-Extra: dev
Requires-Dist: black; extra == "dev"
Requires-Dist: isort; extra == "dev"
Requires-Dist: jupyter; extra == "dev"
Requires-Dist: pydocstyle; extra == "dev"
Requires-Dist: pylint; extra == "dev"
Requires-Dist: pytest; extra == "dev"
Requires-Dist: pytest-cov; extra == "dev"
Dynamic: license-file
